{
    "id": "CW10112009",
    "機構名稱": "新北市私立哈寶寶托嬰中心",
    "所在地": "221新北市汐止區建成路56巷27號2樓",
    "負責人姓名": "吳美玲",
    "聯絡電話": "02-26416401",
    "核定收托": 15,
    "實際收托": 12,
    "評鑑等級": "乙等",
    "最近一次評鑑年度": "108",
    "總面積": "107.82 平方公尺",
    "室內面積": "53.44 平方公尺",
    "室外面積": "0 平方公尺",
    "公共安全說明": "核備文號:108-K008671-01(核備日期:1081105)",
    "消防安全說明": "核備文號:2019年下半年(核備日期:1081030)",
    "準公共化資格": "是",
    "核備工作人員數": {
        "主管人員": "1",
        "托育人員": "4",
        "特約醫師": "1",
        "專任護理人員": "0",
        "行政人員": "0",
        "廚工": "1",
        "其他人員": "0"
    },
    "收費情形": {
        "日間托育": [
            {
                "費用名稱": "托育費",
                "費用金額": "21000",
                "費用說明": ""
            },
            {
                "費用名稱": "其他",
                "費用金額": "0",
                "費用說明": "延托費半小時95元，1小時190元"
            }
        ]
    },
    "退費說明": "依托嬰中心定型化契約內容辦理相關退費事宜",
    "違反法令紀錄": [],
    "latitude": 25.073373403354328,
    "longitude": 121.663033853306
}