{
    "id": "CW10510007",
    "機構名稱": "新北市私立鵝芽芽托嬰中心",
    "所在地": "221新北市汐止區大同路二段184巷13號1樓",
    "負責人姓名": "劉靜慧",
    "聯絡電話": "02-86463888",
    "核定收托": 22,
    "實際收托": 14,
    "評鑑等級": "甲等",
    "最近一次評鑑年度": "111",
    "總面積": "112.69 平方公尺",
    "室內面積": "78.92 平方公尺",
    "室外面積": "0 平方公尺",
    "公共安全說明": "核備文號:0885第07PLPO1865續保(核備日期:1080917)",
    "消防安全說明": "核備文號:(核備日期:1090311)",
    "準公共化資格": "是",
    "核備工作人員數": {
        "主管人員": "1",
        "托育人員": "4",
        "特約醫師": "0",
        "專任護理人員": "0",
        "行政人員": "0",
        "廚工": "2",
        "其他人員": "2"
    },
    "收費情形": {
        "日間托育": [
            {
                "費用名稱": "托育費",
                "費用金額": "21000",
                "費用說明": "註冊費每年一月七月繳交20000元"
            },
            {
                "費用名稱": "其他",
                "費用金額": "0",
                "費用說明": "園所沒有延托如有突發狀況狀況延托費以半小時計95元,超過半小時未滿一小時以一小時計算190元"
            }
        ]
    },
    "退費說明": "依託嬰中心定型化契約內容辦理相關退費事宜",
    "違反法令紀錄": [],
    "latitude": 25.06356896035137,
    "longitude": 121.65383119751178
}