{
    "機構名稱": "臺北市私立小麥穗托嬰中心",
    "所在地": "105臺北市松山區介壽里光復北路165巷11號1樓",
    "負責人姓名": "張文彥",
    "聯絡電話": "(02)2760-6896",
    "核定收托": "34 人",
    "實際收托": "34 人",
    "評鑑等級": "乙等",
    "最近一次評鑑年度": "110",
    "總面積": "146.52 平方公尺",
    "室內面積": "119.29 平方公尺",
    "室外面積": "0 平方公尺",
    "公共安全說明": "",
    "消防安全說明": "",
    "準公共化資格": "否",
    "核備工作人員數": {
        "主管人員": "1",
        "托育人員": "7",
        "特約醫師": "1",
        "專任護理人員": "0",
        "行政人員": "0",
        "廚工": "0",
        "其他人員": "1"
    },
    "收費情形": {
        "日間托育": [
            {
                "費用名稱": "托育費",
                "費用金額": "26500",
                "費用說明": "平均月費:含註冊費每月7000元(1學期6個月共42000元)+月費19500元"
            }
        ]
    },
    "退費說明": "一、月費收費項目：含托育費11000元、餐點費6550元、教材及材料費1950元。\n二、延托費：延托自 18:30 開始，第一小時內收取 100 元，第二小內時收取 200 元，依此類推\n三、退費規定如下:\n(一)註冊費退費－\n入園未滿兩周(含假日)註冊費全額退款\n入園後兩周未滿四周(含假日)退托,註冊費退還二分之一\n入園後四周未滿六週(含假日)退托,其註冊費退還四分之一\n入園後六周以上(含假日)退托,註冊費不予退費\n(二)月費退費－\n入園未滿兩周(含假日)以實際送托每日 1500 元計算其餘月費退還\n入園兩周以上(含假日)按比例計算收取(19500 元\/30天數)其餘月費退還\n(三)其他說明－\n連續事假(含假日)達 21 天以上者,退實際請假日數 x300 元,請假不連續不予退費 具法定傳染疾病者，需請病假休息至少 7 天(含假日)，並出示醫師證明，退費為實際病假日數 x300 元中心因法定傳染病停課,實際停課天數 x300 元",
    "違反法令紀錄": [],
    "latitude": 25.057440081599236,
    "longitude": 121.55606720867168
}