{
    "id": "CW10112540",
    "機構名稱": "臺北市私立拉斐爾托嬰中心",
    "所在地": "114臺北市內湖區民權東路6段296巷87號1樓",
    "負責人姓名": "張凱媗",
    "聯絡電話": "(02)2630-7001",
    "核定收托": 21,
    "實際收托": 13,
    "評鑑等級": "甲等",
    "最近一次評鑑年度": "110",
    "總面積": "98.70 平方公尺",
    "室內面積": "73.71 平方公尺",
    "室外面積": "0 平方公尺",
    "公共安全說明": "核備文號:B10506240210(核備日期:1051026)",
    "消防安全說明": "核備文號:490513(核備日期:1070830)",
    "準公共化資格": "否",
    "核備工作人員數": {
        "主管人員": "1",
        "托育人員": "5",
        "特約醫師": "2",
        "專任護理人員": "0",
        "行政人員": "0",
        "廚工": "1",
        "其他人員": "3"
    },
    "收費情形": {
        "日間托育": [
            {
                "費用名稱": "其他",
                "費用金額": "28500",
                "費用說明": "平均月費:含註冊費每個月5000元(1學期6個月共3萬元)+月費23500元"
            }
        ]
    },
    "退費說明": "一.月費23500元:含托育費15500元、餐點費3500元、教材及材料費2500元、雜費2000元\n二.延托費:無。\n三逾時費:19:00後，1小時收190元。\n四.退費規定如下:\n(一)註冊費退費:(適應期為5日)\n1.自適應期間屆滿後，未逾一個月終止契約者，退還三分之二費用。\n2.自適應期間屆滿後，逾一個月未逾二個月終止契約者，退還三分之一費用。\n3.自適應期間屆滿後，逾二個月終止契約者，不予退費。\n(二)月費退費:當月已繳月費，按比例依所剩日數退還，每日784元。\n(三)其他說明：\n1.事假:不退費\n2.病假:兒童連續請病假五日以上者，依請假日數退還當月餐點每日117元。(連續請病假係包含例假日計算)\n3.兒童罹患腸病毒、衛生福利部公告之法定傳染病或其他傳染病，或因而配合停托者，依請假日數退還每日新臺幣380 元\n4.因天災、事變或配合全國一致性之政府法令等不可抗力或不可歸責於當事人事由，致本契約所定事項無法履行，雙方均不終止本契約時，關於無法履行期間之退費，依未履行日數退還每日475元",
    "違反法令紀錄": [],
    "latitude": 25.07063070985583,
    "longitude": 121.60809491630602
}