{
    "id": "CW10810013",
    "機構名稱": "臺北市私立藝蘭托嬰中心",
    "所在地": "114臺北市內湖區港都里港墘路84號2樓",
    "負責人姓名": "吳秀蘭",
    "聯絡電話": "(02)2627-9660",
    "核定收托": 29,
    "實際收托": 16,
    "評鑑等級": "乙等",
    "最近一次評鑑年度": "113",
    "總面積": "132.17 平方公尺",
    "室內面積": "102.92 平方公尺",
    "室外面積": "0 平方公尺",
    "公共安全說明": "核備文號:台協查核字第11270487900號(核備日期:1121227)",
    "消防安全說明": "核備文號:750438(核備日期:1140515)",
    "準公共化資格": "是",
    "核備工作人員數": {
        "主管人員": "1",
        "托育人員": "6",
        "特約醫師": "1",
        "專任護理人員": "0",
        "行政人員": "1",
        "廚工": "1",
        "其他人員": "1"
    },
    "收費情形": {
        "日間托育": [
            {
                "費用名稱": "其他",
                "費用金額": "23500",
                "費用說明": "平均月費:含註冊費每月5000元(1學期6個月共30000元)+月費18500元"
            }
        ]
    },
    "退費說明": "一、月費18500元.收費項目:含托育費14500元、餐點費2000元、教材材料費1000元、其他1000元.\n二、延托費：\n(一)單次  18:00-18:30單次65元；18:30-19:00單次85元．\n(二)固定  18:00-18:30每月1100元；18:30-19:00每月1500元． 逾時費：19:00-20:00每半小時95元\/一小時190元．\n三、退費規定如下:\n(一)註冊費退費－1.自適應期間五日屆滿後，未逾一個月終止契約者，退還三分之二費用。2.自適應期間五日屆滿後，逾一個月未逾二個月終止契約者，退還三分之一費用。3.自適應期間五日屆滿後，逾二個月終止契約者，不予退費。\n(二)月費退費－當月已繳月費，按比例依所剩日數退還。每日退還617元\n(三)其他說明－1.保險費自契約終止日之次月起，依所剩月數比例退還。2.事假-停托日數不予退費．3.病假-兒童連續請病假五日以上者，依請假日數退還當月餐點每日67元。(連續請病假係包含例假日計算)　4.法定傳染病防治停托-依請假日數退還平均月費新臺幣 314 元。5.因天災、事變或配合全國一致性之政府法令等不可抗力或不可歸責於當事人事由，致本契約所定事項無法履行，雙方均不終止本契約時，關於無法履行期間之退費，依未履行日數退還平均月費新臺幣 392元辦理。6. 環境準備停托-每半年進行全中心環境消毒清潔準備工作，停托一日當天不予退費.",
    "違反法令紀錄": [],
    "latitude": 25.08067962648302,
    "longitude": 121.57761446110013
}