{
    "id": "CW10410006",
    "機構名稱": "臺北市政府社會局委託社團法人新北市中華國際嬰幼兒發展學會經營管理臺北市舊莊社區公共托育家園",
    "所在地": "115臺北市南港區舊莊里舊莊街1段100號舊莊國小忠孝樓1樓",
    "負責人姓名": "周沛慈",
    "聯絡電話": "0227883976",
    "核定收托": 12,
    "實際收托": 6,
    "評鑑等級": "甲等",
    "最近一次評鑑年度": "111",
    "總面積": "112.73 平方公尺",
    "室內面積": "74.53 平方公尺",
    "室外面積": "0 平方公尺",
    "公共安全說明": "核備文號:103A0119841(核備日期:1041008)",
    "消防安全說明": "核備文號:694677(核備日期:1121108)",
    "準公共化資格": "是",
    "核備工作人員數": {
        "主管人員": "1",
        "托育人員": "3",
        "特約醫師": "0",
        "專任護理人員": "0",
        "行政人員": "0",
        "廚工": "0",
        "其他人員": "1"
    },
    "收費情形": {
        "日間托育": [
            {
                "費用名稱": "托育費",
                "費用金額": "14500",
                "費用說明": ""
            }
        ]
    },
    "退費說明": "退費項目-退費標準-備註\n1.新生退托-新入單位未滿半個月申請退托者，退月費四分之一；滿半個月申請退托者，不予退費。\n2.已入托之舊生退托-未滿半個月申請退托者，退月費二分之一；滿半個月申請退托者，不予退費。\n3.事假-不予退費-事假係指嬰幼兒之家屬或實際照顧者因事致嬰幼兒無法就托。\n4.病假-連續請假滿10天以上不含例假日者，退還請假日數三分之一費用。-需檢具醫生診斷證明。\n5.傳染病防治停托-退還停托日數二分之一費用。\n6.環境準備停托-單位每學期開學前停托2日，進行全單位消毒清潔及環境準備工作，不予退費。\n7.國定假日、週休二日及行政院人事行政總處公告放假日-不予退費。\n延托逾時費用採累加制\n17:31~18:00收60元，\n18:01~18:30收60元\n18:31~19:00收100元",
    "違反法令紀錄": [],
    "latitude": 25.040269061906365,
    "longitude": 121.61957537678855
}