{
    "id": "CW10311008",
    "機構名稱": "臺北市私立貝兒托嬰中心",
    "所在地": "112臺北市北投區吉利街158號1樓",
    "負責人姓名": "林宏健",
    "聯絡電話": "02-28280818",
    "核定收托": 38,
    "實際收托": 36,
    "評鑑等級": "甲等",
    "最近一次評鑑年度": "113",
    "總面積": "163.05 平方公尺",
    "室內面積": "137.5 平方公尺",
    "室外面積": "0 平方公尺",
    "公共安全說明": "核備文號:北市公安字第11180559500(核備日期:1111122)",
    "消防安全說明": "核備文號:(核備日期:1121117)",
    "準公共化資格": "是",
    "核備工作人員數": {
        "主管人員": "1",
        "托育人員": "9",
        "特約醫師": "1",
        "專任護理人員": "0",
        "行政人員": "0",
        "廚工": "1",
        "其他人員": "0"
    },
    "收費情形": {
        "日間托育": [
            {
                "費用名稱": "其他",
                "費用金額": "22500",
                "費用說明": "平均月費22,500元計算:註冊費每月2,500元(1學期6個月共15,000元 )+月費20000元"
            }
        ]
    },
    "退費說明": "一、月費 20,000元 收費項目 : 含托育費 17,500元 、餐點費 1,500元、教材材料費 1,000元。\n二、延托費收費：\n（一）單次延托時段及收費：17:30~18:00，65元\/半小時。   18:00~18:30，65元\/半小時。\n（二）固定延托時段及收費：17:30~18:00，550元\/月 。        18:00~18:30，1,100元\/月。\n三、逾時費：無。\n四、退費規定如下:\n(一)註冊費退費 :  1.自適應期間屆滿後，未逾 一個月終止契約者，退還三分之二費用。\n2.自適應期間屆滿後，逾一個月未逾二個月終止契約者，退還三分之一費用。\n3.自適應期間屆滿後，逾二個月終止契約者，不予退費。\n(二)月費退費 : 月費、餐點(含副食品)費：當月已繳月費、餐點(含副食品)費，按比例依所剩日數退還。 (月費退費：667元\/日)\n(三)其他退費說明:\n1.事假退費 : 無。\n2.病假退費: ﹡兒童連續請病假5日以上者，依請假日數退還當月餐點 (含副食品)費。(連續請病假包含例假日計算)\n3.傳染病停托及配合停托退費 : 兒童罹患腸病毒、衛生福利部公告之法定傳染病或其他傳染病，或因而配合停托者，依請假日數退還300元\/日。\n4.天災事故政府一致性停課退費 : 因天災、事變或配合全國一致性之政府法令等不可抗力 或不可歸責於當事人事由，致本契約所定事項無法履行，雙方均不終止本契 約時，關於無法履行期間之退費，依未履行日數退還375元\/日。\n5.其他退費 : 本托嬰中心於每年1月～12月當中，不定期作全中心消毒，為期實施一日。屆時消毒日將於二個月前，公告通知停托日，屆時嬰幼兒  請自行照顧，無退費。",
    "違反法令紀錄": [],
    "latitude": 25.118553,
    "longitude": 121.508648
}