{
    "id": "CW10407010",
    "機構名稱": "新北市私立花園寶寶托嬰中心",
    "所在地": "231新北市新店區中興路2段188號2樓",
    "負責人姓名": "陳星妤",
    "聯絡電話": "29139403",
    "核定收托": 85,
    "實際收托": 25,
    "評鑑等級": "丙等",
    "最近一次評鑑年度": "111",
    "總面積": "422.14 平方公尺",
    "室內面積": "298.37 平方公尺",
    "室外面積": "0 平方公尺",
    "公共安全說明": "核備文號:北工使字第112K01492401號(核備日期:1121208)",
    "消防安全說明": "核備文號:786497(核備日期:1121130)",
    "準公共化資格": "否",
    "核備工作人員數": {
        "主管人員": "1",
        "托育人員": "7",
        "特約醫師": "0",
        "專任護理人員": "0",
        "行政人員": "1",
        "廚工": "2",
        "其他人員": "2"
    },
    "收費情形": {
        "日間托育": [
            {
                "費用名稱": "托育費",
                "費用金額": "21000",
                "費用說明": "含伙食費、材料費、教材使用費"
            },
            {
                "費用名稱": "餐點費",
                "費用金額": "1000",
                "費用說明": "1歲以下500元\/月，1歲以上1000元\/月"
            }
        ]
    },
    "退費說明": "依托嬰中心定型化契約內容辦理相關退費事宜",
    "違反法令紀錄": [],
    "latitude": 24.97282280194448,
    "longitude": 121.54836254719307
}