{
    "id": "CW10408011",
    "機構名稱": "新竹市私立恩潔托嬰中心少年分園",
    "所在地": "300新竹市北區民富里少年街43-1號1-2樓及45號1-2樓",
    "負責人姓名": "程馨儀",
    "聯絡電話": "5250405",
    "核定收托": 41,
    "實際收托": 41,
    "評鑑等級": "優等",
    "最近一次評鑑年度": "107",
    "總面積": "182.09 平方公尺",
    "室內面積": "145.72 平方公尺",
    "室外面積": "0 平方公尺",
    "公共安全說明": "核備文號:府工使字第1080175030號(核備日期:1081127)",
    "消防安全說明": "",
    "準公共化資格": "是",
    "核備工作人員數": {
        "主管人員": "1",
        "托育人員": "11",
        "特約醫師": "0",
        "專任護理人員": "0",
        "行政人員": "0",
        "廚工": "0",
        "其他人員": "0"
    },
    "收費情形": {
        "日間托育": [
            {
                "費用名稱": "托育費",
                "費用金額": "16000",
                "費用說明": "如遇優惠活動期間，另有折扣"
            },
            {
                "費用名稱": "其他",
                "費用金額": "4000",
                "費用說明": "註冊費"
            }
        ]
    },
    "退費說明": "",
    "違反法令紀錄": [],
    "latitude": 24.8060230780568,
    "longitude": 120.95968739207488
}