{
    "id": "CW10901006",
    "機構名稱": "新北市私立安琪寶貝蒙特梭利托嬰中心",
    "所在地": "244新北市林口區民權路153號1、2樓",
    "負責人姓名": "黃文德",
    "聯絡電話": "02-26089239",
    "核定收托": 30,
    "實際收托": 27,
    "評鑑等級": "乙等",
    "最近一次評鑑年度": "111",
    "總面積": "140.07 平方公尺",
    "室內面積": "105.05 平方公尺",
    "室外面積": "0 平方公尺",
    "公共安全說明": "核備文號:108-K010537-01(核備日期:1081210)",
    "消防安全說明": "核備文號:543856(核備日期:1081209)",
    "準公共化資格": "是",
    "核備工作人員數": {
        "主管人員": "0",
        "托育人員": "8",
        "特約醫師": "1",
        "專任護理人員": "0",
        "行政人員": "1",
        "廚工": "1",
        "其他人員": "4"
    },
    "收費情形": {
        "日間托育": [
            {
                "費用名稱": "托育費",
                "費用金額": "20000",
                "費用說明": "註冊費(半年)24000，月費16000"
            }
        ]
    },
    "退費說明": "新北市私立安琪寶貝蒙特梭利托嬰中心  收退費辦法:\n一、延托費說明：本中心收托時間為上午7:30至下午17:30，幼兒逾時仍需留滯於中心時，應支付逾時費用:\n1.延長托育費:每半小時新臺幣80元，第2小時起每半小時新臺幣100元。\n2.逾時費:逾收托時段第3個小時起每半小時新臺幣140元。逾時不滿三十分鐘者，以半小時計，三十分鐘以上未滿一小時者，以一小時計。\n以上依直轄市、縣(市)政府訂定公告之標準收取。\n二、退費標準說明：\n(一)註冊費：\n1.自適應期間屆滿後，未逾一個月終止契約者，退還三分之二費用。\n2.自適應期間屆滿後，逾一個月未逾二個月終止契約者，退還三分之一費用。\n3.自適應期間屆滿後，逾二個月終止契約者，不予退費。\n(二)月費、餐點(含副食品)費：當月已繳月費、餐點(含副食品)費，按比例依所剩日數退還。\n保險費自契約終止日之次月起，依所剩月數比例退還。\n托嬰中心應於收費通知單及繳費收據上載明契約起迄日期，以為退費計算基準，月費以每月三十日計算，退費時按比例依據日數核算。\n三、請假退費方式\n兒童連續請病假五日以上者，依請假日數退還當月餐點(含副食品)費，每日新臺幣100元。(連續請病假係包含例假日計算)\n兒童罹患腸病毒、衛生福利部公告之法定傳染病或其他傳染病，或因而配合停托者，依請假日數退費每日新臺幣267元(每日不得少於平均月費每日費用百分之四十)。(平均月費:指學期註冊費除以六個月，再加上月費，平均月費再除以30為平均月費之每日費用)\n因天災、事變或配合全國一致性之政府法令等不可抗力或不可歸責於當事人事由，致本契約所定事項無法履行，雙方均不終止本契約時，關於無法履行期間之退費，依未履行日數退費每日新臺幣333元(每日不得少於平均月費每日費用百分之五十)辦理。\n(3) 因停課退費，所退費用可折抵次月月費。但若需退費而次月不就讀，則於最後一個送托日起一週內退費。",
    "違反法令紀錄": [],
    "latitude": 25.083780967445623,
    "longitude": 121.37386139761517
}