{
    "id": "CW11401005",
    "機構名稱": "新竹縣公設民營松柏托嬰中心",
    "所在地": "304新竹縣新豐鄉松林村康樂路一段516號2樓",
    "負責人姓名": "台灣聚焦兒童發展協會潘玉娟",
    "聯絡電話": "0986663628",
    "核定收托": 40,
    "實際收托": 36,
    "評鑑等級": "",
    "最近一次評鑑年度": "",
    "總面積": "391.09 平方公尺",
    "室內面積": "152.54 平方公尺",
    "室外面積": "0 平方公尺",
    "公共安全說明": "",
    "消防安全說明": "",
    "準公共化資格": "是",
    "核備工作人員數": {
        "主管人員": "1",
        "托育人員": "10",
        "特約醫師": "1",
        "專任護理人員": "0",
        "行政人員": "0",
        "廚工": "1",
        "其他人員": "0"
    },
    "收費情形": [],
    "退費說明": "",
    "違反法令紀錄": [],
    "latitude": 24.874987,
    "longitude": 120.985566
}