{
    "id": "CW11011007",
    "機構名稱": "臺中市私立喬凱立托嬰中心",
    "所在地": "406臺中市北屯區和平里建和路二段239號",
    "同一地址註記": "　　",
    "負責人姓名": "黃采芝",
    "聯絡電話": "24366869",
    "核定收托": 94,
    "實際收托": 63,
    "評鑑等級": "甲等",
    "最近一次評鑑年度": "112",
    "總面積": "279.34 平方公尺",
    "室內面積": "188.26 平方公尺",
    "室外面積": "331.56 平方公尺",
    "公共安全說明": "核備文號:M11208240277(核備日期:1121207)",
    "消防安全說明": "核備文號:306728(核備日期:1130530)",
    "準公共化資格": "是",
    "核備工作人員數": {
        "主管人員": "1",
        "托育人員": "15",
        "特約醫師": "0",
        "專任護理人員": "0",
        "行政人員": "0",
        "廚工": "0",
        "其他人員": "0"
    },
    "收費情形": {
        "日間托育": [
            {
                "費用名稱": "托育費",
                "費用金額": "17640",
                "費用說明": "註冊費24,000月費12,640"
            },
            {
                "費用名稱": "餐點費",
                "費用金額": "1000",
                "費用說明": ""
            }
        ]
    },
    "退費說明": "第18條終止契約退費方式：\n兒童家長於服務起始日前終止契約，托嬰中心應於終止日起七日內全數退還已繳之註冊費。\n雙方當事人於適應期間得隨時終止契約，托嬰中心應於終止日起七日內，依實際收托日數按比例退還預付之費用。\n因第14條至第16條之事由終止本契約時，已繳之註冊費、月費及餐點費，托嬰中心應於終止日起七日內，按比例將剩餘日數之費用，退還予家長。\n家長得於適應期間屆滿後依第17條規定隨時終止契約，托嬰中心應於終止日起7日內退還款項\n(一)註冊費：\n1.自適應期間屆滿後，未逾一個月終止契約者，退還三分之二費用。\n2.自適應期間屆滿後，逾一個月未逾二個月終止契約者，退還三分之一費用。\n3.自適應期間屆滿後，逾二個月終止契約者，不予退費。\n(二)月費、餐點(含副食品)費：當月已繳月費、餐點(含副食品)費，按比例依所剩日數退還。\n(三)保險費自契約終止日之次月起，依所剩月數比例退還。\n托嬰中心應於收費通知單及繳費收據上載明契約起迄日期，以為退費計算基準，月費以每月三十日計算，退費時按比例依據日數核算。\n\n第19條請假退費方式：\n兒童連續請病假五日以上者(包含例假日)，依請假日數退還當月餐點費。\n兒童罹患腸病毒、衛生福利部公告之法定傳染病或其他傳染病，或因而配合停托者，依請假日數退還平均月費新臺幣222元(不得少於百分之四十)。(平均月費:指學期註冊費除以六個月，再加上月費)\n\n第21條雙方當事人均不終止契約之退費方式：\n因天災、事變或配合全國一致性之政府法令等不可抗力或不可歸責於當事人事由，致本契約所定事項無法履行，雙方均不終止本契約時，關於無法履行期間之退費，依未履行日數退還平均月費新臺幣278元辦理 (不得少於百分之五十)。(平均月費:指學期註冊費除以六個月，再加上月費)",
    "違反法令紀錄": [],
    "latitude": 24.17357542322377,
    "longitude": 120.72448594953782
}