{
    "id": "CW11401001",
    "機構名稱": "好優文教有限公司附設臺南市私立好好美育文平托嬰中心",
    "所在地": "708臺南市安平區建平七街306號1-2樓",
    "負責人姓名": "好優文教有限公司",
    "聯絡電話": "06-2930333",
    "核定收托": 47,
    "實際收托": 23,
    "評鑑等級": "",
    "最近一次評鑑年度": "",
    "總面積": "164.98 平方公尺",
    "室內面積": "164.98 平方公尺",
    "室外面積": "0 平方公尺",
    "公共安全說明": "",
    "消防安全說明": "",
    "準公共化資格": "是",
    "核備工作人員數": {
        "主管人員": "1",
        "托育人員": "7",
        "特約醫師": "0",
        "專任護理人員": "0",
        "行政人員": "0",
        "廚工": "1",
        "其他人員": "0"
    },
    "收費情形": {
        "日間托育": [
            {
                "費用名稱": "教材費",
                "費用金額": "3000",
                "費用說明": "即每月註冊費，每學期註冊費為18000元"
            },
            {
                "費用名稱": "托育費",
                "費用金額": "15800",
                "費用說明": "月費"
            },
            {
                "費用名稱": "餐點費",
                "費用金額": "2000",
                "費用說明": "副食品費"
            }
        ]
    },
    "退費說明": "臺南市公告訂定托嬰中心延長托育費及逾時費之收費標準：\n\n一、延長托育費：依據當年度勞動部公告勞工每小時基本工資。\n二、逾時費：依據當年度勞動部公告勞工每小時基本工資x1.5倍。",
    "違反法令紀錄": [],
    "latitude": 22.989048,
    "longitude": 120.178702
}