{
    "id": "CW11109023",
    "機構名稱": "雲林縣私立榮育鑀托嬰中心",
    "所在地": "632雲林縣虎尾鎮中山里德興路31、33號",
    "負責人姓名": "許建榮",
    "聯絡電話": "(05)6328697",
    "核定收托": 71,
    "實際收托": 70,
    "評鑑等級": "",
    "最近一次評鑑年度": "",
    "總面積": "429.5 平方公尺",
    "室內面積": "253.9 平方公尺",
    "室外面積": "0 平方公尺",
    "公共安全說明": "",
    "消防安全說明": "",
    "準公共化資格": "是",
    "核備工作人員數": {
        "主管人員": "1",
        "托育人員": "17",
        "特約醫師": "0",
        "專任護理人員": "0",
        "行政人員": "0",
        "廚工": "0",
        "其他人員": "0"
    },
    "收費情形": {
        "日間托育": [
            {
                "費用名稱": "托育費",
                "費用金額": "13650",
                "費用說明": ""
            },
            {
                "費用名稱": "餐點費",
                "費用金額": "1500",
                "費用說明": ""
            },
            {
                "費用名稱": "其他",
                "費用金額": "666",
                "費用說明": "註冊費4000一學期六個月"
            }
        ]
    },
    "退費說明": "",
    "違反法令紀錄": [],
    "latitude": 23.708167,
    "longitude": 120.431882
}