{
    "id": "CW10112103",
    "機構名稱": "桃園市私立宜禾托嬰中心",
    "所在地": "338桃園市蘆竹區中山路167號1-3樓、169號1樓",
    "負責人姓名": "楊遵隆",
    "聯絡電話": "03-3118222",
    "核定收托": 40,
    "實際收托": 31,
    "評鑑等級": "甲等",
    "最近一次評鑑年度": "111",
    "總面積": "212.12 平方公尺",
    "室內面積": "144.25 平方公尺",
    "室外面積": "0 平方公尺",
    "公共安全說明": "核備文號:108-B005023-01(核備日期:1081009)",
    "消防安全說明": "核備文號:309515(核備日期:1081215)",
    "準公共化資格": "是",
    "核備工作人員數": {
        "主管人員": "1",
        "托育人員": "9",
        "特約醫師": "0",
        "專任護理人員": "0",
        "行政人員": "0",
        "廚工": "0",
        "其他人員": "0"
    },
    "收費情形": {
        "日間托育": [
            {
                "費用名稱": "托育費",
                "費用金額": "20790",
                "費用說明": "註冊費24000\/6個月+16790"
            },
            {
                "費用名稱": "餐點費",
                "費用金額": "1000",
                "費用說明": ""
            },
            {
                "費用名稱": "其他",
                "費用金額": "1000",
                "費用說明": "書包500餐袋500"
            }
        ]
    },
    "退費說明": "依衛福部定型化契約應記載及不得記載事項辦理。",
    "違反法令紀錄": [],
    "latitude": 25.05732,
    "longitude": 121.297186
}