{
    "id": "CW11404004",
    "機構名稱": "桃園市私立好日子托嬰中心",
    "所在地": "330桃園市桃園區中興里33鄰民安路69號1-2樓",
    "負責人姓名": "楊忠諺",
    "聯絡電話": "03-3369869",
    "核定收托": 42,
    "實際收托": 28,
    "評鑑等級": "",
    "最近一次評鑑年度": "",
    "總面積": "208.16 平方公尺",
    "室內面積": "150.06 平方公尺",
    "室外面積": "150.06 平方公尺",
    "公共安全說明": "",
    "消防安全說明": "",
    "準公共化資格": "是",
    "核備工作人員數": {
        "主管人員": "1",
        "托育人員": "9",
        "特約醫師": "0",
        "專任護理人員": "0",
        "行政人員": "0",
        "廚工": "1",
        "其他人員": "1"
    },
    "收費情形": {
        "日間托育": [
            {
                "費用名稱": "托育費",
                "費用金額": "21000",
                "費用說明": "平均月費(註冊費\/6=3000+月費18000)"
            },
            {
                "費用名稱": "餐點費",
                "費用金額": "1200",
                "費用說明": ""
            }
        ]
    },
    "退費說明": "(一)註冊費：新臺幣(以下同)1萬8,000元(以6個月計)。\n(二)月費：1萬8,000元。\n(三)保險費(代收代付)：依當年度政府公告托嬰中心辦理兒童團體保險規定收取。\n(四)餐點(含副食品)費：1,200元\/月。\n(五)延長托育費：每小時新臺幣每小時基本時薪X1.34倍元（依直轄市、縣(市)政府訂定公告之逾時費標準收取）。逾時不滿30分鐘者，以半小時計，30分鐘以上未滿1小時者，以1小時計。常態性延托-包月每時段收取之金額：\n１、7時至7時29分，每月費用新台幣1,400 元。\n２、17時31分至18時，每月費用新台幣1,400 元。\n３、17時31至18時30分，每月費用新台幣2,800元。\n(六)逾時費：逾收托時段每小時新臺幣每小時基本時薪X1.34倍元（依直轄市、縣(市)政府訂定公告之逾時費標準收取）。逾時不滿30分鐘者，以半小時計，30分鐘以上未滿1小時者，以1小時計。\n(七)其他經直轄市、縣(市)政府核定可收取之費用：一次性費\n用代辦，由家長自行選購：１、書包：新台幣600。２、餐具組袋：新台幣800 元，含 3 色碗、1 個餐袋。３、寢具袋：新台幣600 元。４、幼兒圍兜： 新台幣300 元。５、防水隔尿墊：新台幣500 元。６、床包：新台幣500元。",
    "違反法令紀錄": [],
    "latitude": 24.997603,
    "longitude": 121.299976
}