{
    "id": "CW11202005",
    "機構名稱": "桃園市私立童萌國托嬰中心",
    "所在地": "333桃園市龜山區大華里9鄰文化七路74號1-3樓",
    "負責人姓名": "謝長霖",
    "聯絡電話": "03-3281618",
    "核定收托": 38,
    "實際收托": 38,
    "評鑑等級": "",
    "最近一次評鑑年度": "",
    "總面積": "184.89 平方公尺",
    "室內面積": "76.55 平方公尺",
    "室外面積": "70.69 平方公尺",
    "公共安全說明": "",
    "消防安全說明": "",
    "準公共化資格": "是",
    "核備工作人員數": {
        "主管人員": "1",
        "托育人員": "23",
        "特約醫師": "0",
        "專任護理人員": "0",
        "行政人員": "0",
        "廚工": "2",
        "其他人員": "2"
    },
    "收費情形": {
        "日間托育": [
            {
                "費用名稱": "托育費",
                "費用金額": "20000",
                "費用說明": "註冊費24000(6個月計)及月費16000元"
            },
            {
                "費用名稱": "餐點費",
                "費用金額": "1000",
                "費用說明": ""
            },
            {
                "費用名稱": "其他",
                "費用金額": "2700",
                "費用說明": "代辦費(書包350、餐具組300、餐袋150、床墊900)、沐浴費1000\/每月"
            }
        ]
    },
    "退費說明": "",
    "違反法令紀錄": [],
    "latitude": 25.051318559514876,
    "longitude": 121.36341385287743
}