{
    "id": "CW10710008",
    "機構名稱": "苗栗縣私立彩虹森林托嬰中心",
    "所在地": "351苗栗縣頭份市蟠桃里自立街56號1樓",
    "負責人姓名": "陳彥愷",
    "聯絡電話": "037-668385",
    "核定收托": 20,
    "實際收托": 0,
    "評鑑等級": "乙等",
    "最近一次評鑑年度": "110",
    "總面積": "119.91 平方公尺",
    "室內面積": "71.59 平方公尺",
    "室外面積": "0 平方公尺",
    "公共安全說明": "",
    "消防安全說明": "",
    "準公共化資格": "是",
    "核備工作人員數": {
        "主管人員": "0",
        "托育人員": "0",
        "特約醫師": "0",
        "專任護理人員": "0",
        "行政人員": "0",
        "廚工": "0",
        "其他人員": "0"
    },
    "收費情形": {
        "日間托育": [
            {
                "費用名稱": "其他",
                "費用金額": "2000",
                "費用說明": "註冊費(6個月)"
            },
            {
                "費用名稱": "托育費",
                "費用金額": "15400",
                "費用說明": ""
            },
            {
                "費用名稱": "餐點費",
                "費用金額": "2000",
                "費用說明": "6個月前為沐浴費、6個月後為副食品費"
            }
        ]
    },
    "退費說明": "",
    "違反法令紀錄": [],
    "latitude": 24.690828252436276,
    "longitude": 120.90554562054564
}